{
  "$schema": "https://qstxiv.github.io/schema/gatheringlocation-v1.json",
  "Author": "alydev",
  "Steps": [
    {
      "TerritoryId": 153,
      "InteractionType": "None"
    }
  ],
  "Groups": [
    {
      "Nodes": [
        {
          "DataId": 30360,
          "Locations": [
            {
              "Position": {
                "X": -37.77211,
                "Y": 2.572128,
                "Z": 432.912
              }
            },
            {
              "Position": {
                "X": -19.97406,
                "Y": 2.17493,
                "Z": 427.7867
              }
            },
            {
              "Position": {
                "X": -42.19049,
                "Y": 2.492494,
                "Z": 425.0606
              }
            }
          ]
        },
        {
          "DataId": 30359,
          "Locations": [
            {
              "Position": {
                "X": 7.099764,
                "Y": 2.575975,
                "Z": 372.4252
              }
            },
            {
              "Position": {
                "X": 5.028318,
                "Y": 1.314106,
                "Z": 350.6096
              }
            },
            {
              "Position": {
                "X": 12.26667,
                "Y": 2.654378,
                "Z": 397.215
              }
            }
          ]
        },
        {
          "DataId": 30358,
          "Locations": [
            {
              "Position": {
                "X": 23.28186,
                "Y": 3.55986,
                "Z": 309.1969
              }
            },
            {
              "Position": {
                "X": 28.27769,
                "Y": 3.450384,
                "Z": 338.3645
              }
            },
            {
              "Position": {
                "X": 19.61104,
                "Y": 3.109716,
                "Z": 335.3041
              }
            }
          ]
        },
        {
          "DataId": 30357,
          "Locations": [
            {
              "Position": {
                "X": -4.51515,
                "Y": 2.614629,
                "Z": 298.8632
              }
            },
            {
              "Position": {
                "X": 0.6866455,
                "Y": 2.749068,
                "Z": 301.1367
              }
            },
            {
              "Position": {
                "X": -7.675354,
                "Y": 2.684879,
                "Z": 301.2893
              }
            }
          ]
        }
      ]
    }
  ]
}