{
  "$schema": "https://qstxiv.github.io/schema/gatheringlocation-v1.json",
  "Author": "alydev",
  "Steps": [
    {
      "TerritoryId": 153,
      "InteractionType": "None"
    }
  ],
  "Groups": [
    {
      "Nodes": [
        {
          "DataId": 31036,
          "Locations": [
            {
              "Position": {
                "X": -246.3576,
                "Y": 16.52244,
                "Z": 82.03388
              },
              "MinimumAngle": 110,
              "MaximumAngle": 150
            },
            {
              "Position": {
                "X": -161.4515,
                "Y": 10.99831,
                "Z": 88.92267
              },
              "MinimumAngle": -15,
              "MaximumAngle": 55
            },
            {
              "Position": {
                "X": -192.7974,
                "Y": 11.80435,
                "Z": 65.14055
              },
              "MinimumAngle": 0,
              "MaximumAngle": 90,
              "MinimumDistance": 1.9,
              "MaximumDistance": 3
            }
          ]
        }
      ]
    }
  ]
}