{
  "$schema": "https://qstxiv.github.io/schema/gatheringlocation-v1.json",
  "Author": "alydev",
  "Steps": [
    {
      "TerritoryId": 939,
      "InteractionType": "None"
    }
  ],
  "Groups": [
    {
      "Nodes": [
        {
          "DataId": 33644,
          "Locations": [
            {
              "Position": {
                "X": -579.3251,
                "Y": 34.96582,
                "Z": -234.6397
              },
              "MinimumAngle": -165,
              "MaximumAngle": -85
            }
          ]
        },
        {
          "DataId": 33696,
          "Locations": [
            {
              "Position": {
                "X": -393.1422,
                "Y": 22.68014,
                "Z": -252.6048
              },
              "MinimumAngle": -320,
              "MaximumAngle": -280
            },
            {
              "Position": {
                "X": -396.0591,
                "Y": 23.01282,
                "Z": -255.7066
              },
              "MinimumAngle": 70,
              "MaximumAngle": 120
            }
          ]
        },
        {
          "DataId": 33649,
          "Locations": [
            {
              "Position": {
                "X": -327.9103,
                "Y": -3.49421,
                "Z": -450.3215
              },
              "MinimumAngle": -90,
              "MaximumAngle": 0
            },
            {
              "Position": {
                "X": -333.5058,
                "Y": -3.714353,
                "Z": -445.2068
              },
              "MinimumAngle": -75,
              "MaximumAngle": 0
            }
          ]
        },
        {
          "DataId": 33656,
          "Locations": [
            {
              "Position": {
                "X": 48.55704,
                "Y": -20.71149,
                "Z": -629.5051
              },
              "MinimumAngle": -45,
              "MaximumAngle": 0
            },
            {
              "Position": {
                "X": 53.76094,
                "Y": -20.83158,
                "Z": -632.3669
              },
              "MinimumAngle": -80,
              "MaximumAngle": 25
            }
          ]
        },
        {
          "DataId": 33703,
          "Locations": [
            {
              "Position": {
                "X": -45.59274,
                "Y": -46.60242,
                "Z": -513.2087
              },
              "MinimumAngle": -310,
              "MaximumAngle": -260
            },
            {
              "Position": {
                "X": -47.83794,
                "Y": -46.82134,
                "Z": -520.8481
              },
              "MinimumAngle": -305,
              "MaximumAngle": -245
            }
          ]
        },
        {
          "DataId": 33710,
          "Locations": [
            {
              "Position": {
                "X": 490.8867,
                "Y": 195.6942,
                "Z": -668.16
              },
              "MinimumAngle": -225,
              "MaximumAngle": -190
            },
            {
              "Position": {
                "X": 493.3243,
                "Y": 195.6406,
                "Z": -671.3446
              },
              "MinimumAngle": -295,
              "MaximumAngle": -270
            }
          ]
        },
        {
          "DataId": 33663,
          "Locations": [
            {
              "Position": {
                "X": 504.9699,
                "Y": 198.8839,
                "Z": -631.6051
              },
              "MinimumAngle": -15,
              "MaximumAngle": 0
            },
            {
              "Position": {
                "X": 507.4546,
                "Y": 199.1226,
                "Z": -626.0507
              },
              "MinimumAngle": -220,
              "MaximumAngle": -195
            }
          ]
        },
        {
          "DataId": 33715,
          "Locations": [
            {
              "Position": {
                "X": 724.2842,
                "Y": 221.5456,
                "Z": -292.9167
              },
              "MinimumAngle": -225,
              "MaximumAngle": -215
            },
            {
              "Position": {
                "X": 724.4434,
                "Y": 220.6098,
                "Z": -296.8843
              },
              "MinimumAngle": 45,
              "MaximumAngle": 75
            }
          ]
        },
        {
          "DataId": 33717,
          "Locations": [
            {
              "Position": {
                "X": 736.1116,
                "Y": 221.1883,
                "Z": -172.6939
              },
              "MinimumAngle": -265,
              "MaximumAngle": -245
            },
            {
              "Position": {
                "X": 733.8794,
                "Y": 221.5866,
                "Z": -170.3233
              },
              "MinimumAngle": -200,
              "MaximumAngle": -180
            }
          ]
        },
        {
          "DataId": 33670,
          "Locations": [
            {
              "Position": {
                "X": 658.9163,
                "Y": 224.5736,
                "Z": -149.48
              },
              "MinimumAngle": -155,
              "MaximumAngle": -105
            },
            {
              "Position": {
                "X": 663.1543,
                "Y": 224.4664,
                "Z": -157.2901
              },
              "MinimumAngle": -305,
              "MaximumAngle": -260
            }
          ]
        },
        {
          "DataId": 33722,
          "Locations": [
            {
              "Position": {
                "X": 439.2756,
                "Y": -19.48899,
                "Z": 271.5723
              },
              "MinimumAngle": -165,
              "MaximumAngle": -115
            },
            {
              "Position": {
                "X": 437.7084,
                "Y": -20.16032,
                "Z": 267.9861
              },
              "MinimumAngle": -80,
              "MaximumAngle": -35,
              "MinimumDistance": 1.8,
              "MaximumDistance": 3
            }
          ]
        },
        {
          "DataId": 33724,
          "Locations": [
            {
              "Position": {
                "X": 479.1402,
                "Y": -7.697751,
                "Z": 351.5734
              },
              "MinimumAngle": -210,
              "MaximumAngle": -150
            },
            {
              "Position": {
                "X": 472.6859,
                "Y": -5.507981,
                "Z": 351.4054
              },
              "MinimumAngle": -175,
              "MaximumAngle": -125
            }
          ]
        },
        {
          "DataId": 33675,
          "Locations": [
            {
              "Position": {
                "X": 624.9774,
                "Y": -35.12883,
                "Z": 316.0575
              },
              "MinimumAngle": -280,
              "MaximumAngle": -250
            },
            {
              "Position": {
                "X": 623.3104,
                "Y": -35.01489,
                "Z": 321.1231
              },
              "MinimumAngle": -215,
              "MaximumAngle": -190
            }
          ]
        },
        {
          "DataId": 33677,
          "Locations": [
            {
              "Position": {
                "X": 552.363,
                "Y": -31.3809,
                "Z": 415.4896
              },
              "MinimumAngle": -130,
              "MaximumAngle": -5
            },
            {
              "Position": {
                "X": 551.0145,
                "Y": -31.55103,
                "Z": 421.5515
              },
              "MinimumAngle": -160,
              "MaximumAngle": 0
            }
          ]
        },
        {
          "DataId": 33729,
          "Locations": [
            {
              "Position": {
                "X": 152.491,
                "Y": 87.36201,
                "Z": 543.0953
              },
              "MinimumAngle": -35,
              "MaximumAngle": 40
            },
            {
              "Position": {
                "X": 136.9525,
                "Y": 87.7638,
                "Z": 542.0449
              },
              "MinimumAngle": -105,
              "MaximumAngle": -55
            }
          ]
        },
        {
          "DataId": 33682,
          "Locations": [
            {
              "Position": {
                "X": 78.62807,
                "Y": 89.89125,
                "Z": 603.6975
              },
              "MinimumAngle": -140,
              "MaximumAngle": -75
            },
            {
              "Position": {
                "X": 78.59138,
                "Y": 88.86626,
                "Z": 606.2505
              },
              "MinimumAngle": -125,
              "MaximumAngle": -55
            }
          ]
        },
        {
          "DataId": 33684,
          "Locations": [
            {
              "Position": {
                "X": -59.16573,
                "Y": 114.1943,
                "Z": 680.3058
              },
              "MinimumAngle": -100,
              "MaximumAngle": 0,
              "MinimumDistance": 1,
              "MaximumDistance": 2
            },
            {
              "Position": {
                "X": -55.54385,
                "Y": 113.9906,
                "Z": 672.6223
              },
              "MinimumAngle": -135,
              "MaximumAngle": 0
            }
          ]
        },
        {
          "DataId": 33689,
          "Locations": [
            {
              "Position": {
                "X": -592.5279,
                "Y": 331.0199,
                "Z": 521.6069
              },
              "MinimumAngle": -100,
              "MaximumAngle": -50
            },
            {
              "Position": {
                "X": -588.7994,
                "Y": 330.6688,
                "Z": 525.9655
              },
              "MinimumAngle": -220,
              "MaximumAngle": -185
            }
          ]
        },
        {
          "DataId": 33736,
          "Locations": [
            {
              "Position": {
                "X": -409.9113,
                "Y": 318.4907,
                "Z": 426.9127
              },
              "MinimumAngle": -45,
              "MaximumAngle": 0
            },
            {
              "Position": {
                "X": -397.5243,
                "Y": 318.5621,
                "Z": 426.2635
              },
              "MinimumAngle": -60,
              "MaximumAngle": 55
            }
          ]
        },
        {
          "DataId": 33739,
          "Locations": [
            {
              "Position": {
                "X": -731.6359,
                "Y": 271.6829,
                "Z": -71.96931
              },
              "MinimumAngle": -50,
              "MaximumAngle": 0
            },
            {
              "Position": {
                "X": -731.61,
                "Y": 272.7054,
                "Z": -80.71025
              },
              "MinimumAngle": -90,
              "MaximumAngle": -75,
              "MinimumDistance": 2,
              "MaximumDistance": 3
            }
          ]
        }
      ]
    }
  ]
}