{
  "$schema": "https://qstxiv.github.io/schema/gatheringlocation-v1.json",
  "Author": "alydev",
  "Steps": [
    {
      "TerritoryId": 939,
      "InteractionType": "None"
    }
  ],
  "Groups": [
    {
      "Nodes": [
        {
          "DataId": 33839,
          "Locations": [
            {
              "Position": {
                "X": 384.0722,
                "Y": 294.2122,
                "Z": 583.4051
              },
              "MinimumAngle": -285,
              "MaximumAngle": -225
            },
            {
              "Position": {
                "X": 411.8797,
                "Y": 293.7472,
                "Z": 583.4534
              },
              "MinimumAngle": -140,
              "MaximumAngle": 0
            },
            {
              "Position": {
                "X": 396.4532,
                "Y": 294.1685,
                "Z": 596.3341
              },
              "MinimumAngle": -60,
              "MaximumAngle": 125
            }
          ]
        }
      ]
    }
  ]
}