{
  "$schema": "https://qstxiv.github.io/schema/gatheringlocation-v1.json",
  "Author": "alydev",
  "Steps": [
    {
      "TerritoryId": 401,
      "InteractionType": "None"
    }
  ],
  "Groups": [
    {
      "Nodes": [
        {
          "DataId": 31465,
          "Locations": [
            {
              "Position": {
                "X": 608.8767,
                "Y": -153.4452,
                "Z": 727.9901
              },
              "MinimumAngle": -85,
              "MaximumAngle": 0
            },
            {
              "Position": {
                "X": 665.5395,
                "Y": -157.7969,
                "Z": 826.8955
              },
              "MinimumAngle": -355,
              "MaximumAngle": -190
            }
          ]
        }
      ]
    }
  ]
}