{
  "$schema": "https://qstxiv.github.io/schema/gatheringlocation-v1.json",
  "Author": "alydev",
  "Steps": [
    {
      "TerritoryId": 401,
      "InteractionType": "None"
    }
  ],
  "Groups": [
    {
      "Nodes": [
        {
          "DataId": 31495,
          "Locations": [
            {
              "Position": {
                "X": 524.3884,
                "Y": 17.75531,
                "Z": 28.48951
              },
              "MinimumAngle": -85,
              "MaximumAngle": -55
            }
          ]
        }
      ]
    }
  ]
}